ksmith/__init__.py
ksmith/_ksmith.py
ksmith-0.0.4.dist-info/METADATA
ksmith-0.0.4.dist-info/WHEEL
ksmith-0.0.4.dist-info/top_level.txt
ksmith-0.0.4.dist-info/RECORD
