Metadata-Version: 2.1
Name: ksmith
Version: 0.0.4
Summary: Kent Smith's personnal python library.
Home-page: https://github.com/mehismyname/Ksmith
Author: Kent Smith
License: MIT
Keywords: ksmith
Platform: UNKNOWN
Requires-Python: >= 3.5
